cognite/well_model/README.md
cognite/well_model/__init__.py
cognite/well_model/_version.py
cognite/well_model/base_model.py
cognite/well_model/client/__init__.py
cognite/well_model/client/_api_client.py
cognite/well_model/client/_cognite_wells_client.py
cognite/well_model/client/_http_client.py
cognite/well_model/client/api/__init__.py
cognite/well_model/client/api/api_base.py
cognite/well_model/client/api/casings.py
cognite/well_model/client/api/depth_measurements.py
cognite/well_model/client/api/hole_sections.py
cognite/well_model/client/api/measurement_types.py
cognite/well_model/client/api/merge_rules/__init__.py
cognite/well_model/client/api/merge_rules/wellbores.py
cognite/well_model/client/api/merge_rules/wells.py
cognite/well_model/client/api/mnemonics.py
cognite/well_model/client/api/nds_events.py
cognite/well_model/client/api/npt_events.py
cognite/well_model/client/api/rig_operations.py
cognite/well_model/client/api/sources.py
cognite/well_model/client/api/summaries.py
cognite/well_model/client/api/time_measurements.py
cognite/well_model/client/api/trajectories.py
cognite/well_model/client/api/well_sources.py
cognite/well_model/client/api/well_tops.py
cognite/well_model/client/api/wellbore_sources.py
cognite/well_model/client/api/wellbores.py
cognite/well_model/client/api/wells.py
cognite/well_model/client/models/depth_measurement_rows.py
cognite/well_model/client/models/nds_aggregates.py
cognite/well_model/client/models/npt_aggregates.py
cognite/well_model/client/models/property_filter.py
cognite/well_model/client/models/resource_list.py
cognite/well_model/client/models/trajectory_rows.py
cognite/well_model/client/models/true_vertical_depth_list.py
cognite/well_model/client/models/well_merge_details.py
cognite/well_model/client/models/wellbore_merge_details.py
cognite/well_model/client/utils/__init__.py
cognite/well_model/client/utils/_auxiliary.py
cognite/well_model/client/utils/_client_config.py
cognite/well_model/client/utils/_distance_unit.py
cognite_wells_sdk-0.18.3.dist-info/WHEEL
cognite_wells_sdk-0.18.3.dist-info/METADATA
cognite_wells_sdk-0.18.3.dist-info/RECORD
