Metadata-Version: 2.1
Name: cognite-wells-sdk
Version: 0.18.3
Summary: 
Author: Sigurd Holsen
Author-email: sigurd.holsen@cognite.com
Requires-Python: >=3.8.0,<4.0.0
Classifier: Programming Language :: Python :: 3
Classifier: Programming Language :: Python :: 3.8
Classifier: Programming Language :: Python :: 3.9
Classifier: Programming Language :: Python :: 3.10
Classifier: Programming Language :: Python :: 3.11
Requires-Dist: matplotlib
Requires-Dist: pandas
Requires-Dist: pydantic (>=1.8,<2.0)
Requires-Dist: requests (>=2,<3)
Requires-Dist: requests-oauthlib (>=1,<2)
